{
    "metaDataVersion": "1.0.0",
    "category": "com.microchip.ide.project",
    "content": {
        "metaDataVersion": "1.1.0",
        "name": "com.microchip.mcu8.mplabx.project.pic18f47q10-adc-computation-modes-mplab",
        "version": "1.0.2",
        "displayName": "Usage of PIC18-Q10 family 10-bit ADCC Computation modes for real-time sensing applications",
        "projectName": "pic18f47q10-adc-computation-modes-mplab",
        "shortDescription": "Microchip offers a 10-bit ADCC module in PIC18-Q10 family microcontrollers. This example highlights the basic, average, burst average and low-pass filter computation modes of ADC using PIC18F47Q10 MCU and Curiosity High Pin Count development board.",
        "ide": {
            "name": "MPLAB X",
            "semverRange": ">=5.40.0"
        },
        "compiler": [
			{
				"name": "XC8",
				"semverRange": "^2.30.0"
			}
		],
        "dfp": {
            "name": "PIC18F-Q_DFP",
            "semverRange": "^1.8.154"
        },
        "configurator": {
            "name": "MCC",
            "semverRange": ">=4.0.1"
        },
        "device": {
            "metaDataVersion": "1.0.0",
            "category": "com.microchip.portal.contentRef",
            "content": {
                "metaDataVersion": "1.0.0",
                "category": "com.microchip.device",
                "name": "PIC18F47Q10",
                "versionRange": "*"
            }
        },
        "author": "Microchip",
        "subcategories": [
			"Sensor Nodes",
            [
               "Peripherals", "TMR1"
            ],
            [
               "Peripherals", "ADCC"
            ],
            [
               "Peripherals", "HLT"
            ],
            [
               "Peripherals", "USART"
            ]              			
        ],
        "peripherals": [
            "TMR1","ADCC","HLT","USART"
        ],
        "keywords": [
			"16-bit Timer",
			"Data Visualizer",
			"Average",
			"Curiosity",
			"Switch Debounce",
			"Wired Communication",
			"Computation Modes",
			"Low Pass Filter"
        ],
		"additionalData": {
			"longDescription": {
				"metaDataVersion": "1.0.0",
				"category": "com.microchip.portal.fileRef",
				"content": {
					"metaDataVersion": "1.0.0",
					"fileName": "./README.md",
					"mimeType": "text/markdown"
				}
			}
		}
	}
}
